picaso/__init__.py
picaso/analyze.py
picaso/atmsetup.py
picaso/build_3d_input.py
picaso/cia_interpolate.py
picaso/climate.py
picaso/deq_chem.py
picaso/disco.py
picaso/elements.py
picaso/fluxes.py
picaso/io_utils.py
picaso/justdoit.py
picaso/justplotit.py
picaso/opacity_factory.py
picaso/optics.py
picaso/phasecurves.py
picaso/photochem.py
picaso/rayleigh.py
picaso/references.py
picaso/run_opa_factory.py
picaso/test.py
picaso/test_optics.py
picaso/wavelength.py
picaso-3.4.dist-info/LICENSE
picaso-3.4.dist-info/METADATA
picaso-3.4.dist-info/WHEEL
picaso-3.4.dist-info/top_level.txt
picaso-3.4.dist-info/RECORD
